mousekey/README.MD
mousekey/__init__.py
mousekey/requirements.txt
mousekey/thirdparty.json
mousekey-0.12.dist-info/LICENSE.rst
mousekey-0.12.dist-info/METADATA
mousekey-0.12.dist-info/WHEEL
mousekey-0.12.dist-info/top_level.txt
mousekey-0.12.dist-info/RECORD
