Metadata-Version: 2.1
Name: mousekey
Version: 0.12
Summary: Automates mouse/keyboard, works with games like Roblox!
Home-page: https://github.com/hansalemaos/mousekey
Author: Johannes Fischer
Author-email: aulasparticularesdealemaosp@gmail.com
License: MIT
Keywords: automate,keystroke,mouse,games,pyautogui
Classifier: Development Status :: 4 - Beta
Classifier: Programming Language :: Python :: 3 :: Only
Classifier: Programming Language :: Python :: 3.10
Classifier: Topic :: Software Development :: Libraries :: Python Modules
Classifier: Topic :: Utilities
License-File: LICENSE.rst
Requires-Dist: ctypes-rgb-values
Requires-Dist: ctypes-window-info
Requires-Dist: flatten-everything
Requires-Dist: keyboard
Requires-Dist: kthread
Requires-Dist: numpy
Requires-Dist: six
